{
    "courses": [
        {
            "code": "CENG101",
            "name": "Computer Engineering",
            "year": "2020",
            "duration": "5",
            "active": true
        },
        {
            "code": "CENG102",
            "name": "Computer Engineering",
            "year": "2021",
            "duration": "5",
            "active": true
        },
        {
            "code": "CENG103",
            "name": "Computer Engineering",
            "year": "2022",
            "duration": "5",
            "active": true
        },
        {
            "code": "CENG104",
            "name": "Computer Engineering",
            "year": "2023",
            "duration": "5",
            "active": true
        },
        {
            "code": "CS101",
            "name": "Computer Science",
            "year": "2020",
            "duration": "4",
            "active": true
        },
        {
            "code": "CS102",
            "name": "Computer Science",
            "year": "2021",
            "duration": "4",
            "active": true
        },
        {
            "code": "CS103",
            "name": "Computer Science",
            "year": "2022",
            "duration": "4",
            "active": true
        },
        {
            "code": "CS104",
            "name": "Computer Science",
            "year": "2023",
            "duration": "4",
            "active": true
        }
    ]
}